Metadata-Version: 2.1
Name: em-deepfinder
Version: 1.1.0
Summary: Deep Finder is an original deep learning approach to localize macromolecules in cryo electron tomography images. The method is based on image segmentation using a 3D convolutional neural network.
Author: 
Author-email: 
License: GPL-3.0
Classifier: Development Status :: 4 - Beta
Classifier: Intended Audience :: Developers
Classifier: Intended Audience :: Science/Research
Classifier: Topic :: Scientific/Engineering
Classifier: Topic :: Scientific/Engineering :: Visualization
Classifier: Topic :: Scientific/Engineering :: Information Analysis
Classifier: Topic :: Scientific/Engineering :: Bio-Informatics
Classifier: Topic :: Scientific/Engineering :: Artificial Intelligence
Classifier: Topic :: Scientific/Engineering :: Image Processing
Classifier: Programming Language :: Python
Classifier: Programming Language :: Python :: 3
Classifier: Programming Language :: Python :: 3.8
Classifier: Programming Language :: Python :: 3.9
Classifier: Programming Language :: Python :: 3.10
Classifier: Operating System :: OS Independent
Classifier: License :: OSI Approved :: GNU General Public License v3 (GPLv3)
Requires-Python: >=3.8
License-File: LICENSE
Requires-Dist: tensorflow (==2.8.2)
Requires-Dist: Keras (==2.8.0)
Requires-Dist: h5py (>=3.6.0)
Requires-Dist: lxml (>=4.8.0)
Requires-Dist: mrcfile (>=1.3.0)
Requires-Dist: scikit-learn (>=1.0.2)
Requires-Dist: scikit-image (>=0.19.2)
Requires-Dist: matplotlib (>=3.5.2)
Requires-Dist: PyQt5 (>=5.15.6)
Requires-Dist: pyqtgraph (>=0.12.4)
Requires-Dist: openpyxl (>=3.0.9)
Requires-Dist: scipy (>=1.7.3)
Requires-Dist: numpy
Requires-Dist: pycm
